substrait_validator-0.1.4.dist-info/METADATA
substrait_validator-0.1.4.dist-info/WHEEL
substrait_validator-0.1.4.dist-info/entry_points.txt
substrait_validator-0.1.4.dist-info/license_files/LICENSE
substrait_validator/__init__.py
substrait_validator/substrait/__init__.py
substrait_validator/substrait/algebra_pb2.py
substrait_validator/substrait/capabilities_pb2.py
substrait_validator/substrait/extended_expression_pb2.py
substrait_validator/substrait/extensions/__init__.py
substrait_validator/substrait/extensions/extensions_pb2.py
substrait_validator/substrait/function_pb2.py
substrait_validator/substrait/parameterized_types_pb2.py
substrait_validator/substrait/plan_pb2.py
substrait_validator/substrait/type_expressions_pb2.py
substrait_validator/substrait/type_pb2.py
substrait_validator/substrait/validator/__init__.py
substrait_validator/substrait/validator/simple_extensions_pb2.py
substrait_validator/substrait/validator/tree_pb2.py
substrait_validator/substrait/validator/type_system_pb2.py
substrait_validator/substrait_validator.cpython-312-x86_64-linux-gnu.so
substrait_validator-0.1.4.dist-info/RECORD
