Metadata-Version: 2.1
Name: substrait-validator
Version: 0.1.4
Classifier: Programming Language :: Rust
Classifier: Programming Language :: Python :: Implementation :: CPython
Classifier: Programming Language :: Python :: Implementation :: PyPy
Requires-Dist: protobuf > 3.19.3
Requires-Dist: click >= 8
Requires-Dist: pyyaml >= 6
Requires-Dist: jdot >= 0.5
Requires-Dist: pytest < 9.0.0; extra == 'test'
Requires-Dist: toml >= 0.10.2; extra == 'test'
Provides-Extra: test
License-File: LICENSE
Summary: Validator for Substrait query plans
Keywords: substrait
License: Apache-2.0
Requires-Python: >=3.8
Project-URL: repository, https://github.com/substrait-io/substrait-validator
Project-URL: homepage, https://substrait.io/
